pyarmor_runtime_000000/__init__.py
utils_with_script/__init__.py
utils_with_script/setup.py
utils_with_script/utils_with_script/__init__.py
utils_with_script/utils_with_script/date_utils.py
utils_with_script-0.1.3.dist-info/METADATA
utils_with_script-0.1.3.dist-info/WHEEL
utils_with_script-0.1.3.dist-info/top_level.txt
utils_with_script-0.1.3.dist-info/RECORD
