Metadata-Version: 2.4
Name: utils_with_script
Version: 0.1.3
Summary: A simple Python package for date format
Classifier: Programming Language :: Python :: 3
Classifier: License :: OSI Approved :: MIT License
Classifier: Operating System :: OS Independent
Requires-Python: >=3.6
Dynamic: classifier
Dynamic: requires-python
Dynamic: summary
